codalyzer/__init__.py
codalyzer/core.py
codalyzer-0.1.0.dist-info/licenses/LICENCE
codalyzer-0.1.0.dist-info/METADATA
codalyzer-0.1.0.dist-info/WHEEL
codalyzer-0.1.0.dist-info/top_level.txt
codalyzer-0.1.0.dist-info/RECORD
