Metadata-Version: 2.4
Name: codalyzer
Version: 0.1.0
Summary: Advanced Python code analyzer with regex, colorized output, visual stats, and more.
Home-page: https://github.com/yourusername/codalyzer
Author: Adam Alcander et Eden
Author-email: Adam Alcander et Eden <your.email@example.com>
License: MIT
Keywords: analyzer,python,code,regex,matplotlib,socket,colorama
Classifier: Development Status :: 4 - Beta
Classifier: Intended Audience :: Developers
Classifier: Programming Language :: Python :: 3
Classifier: License :: OSI Approved :: MIT License
Classifier: Operating System :: OS Independent
Requires-Python: >=3.7
License-File: LICENCE
Requires-Dist: matplotlib
Requires-Dist: numpy
Requires-Dist: colorama
Requires-Dist: requests
Requires-Dist: tqdm
Requires-Dist: psutil
Requires-Dist: rich
Requires-Dist: pygments
Requires-Dist: tabulate
Requires-Dist: socketify
Dynamic: author
Dynamic: license-file
Dynamic: requires-python
